Workbook

Sheet Consumer Complaints
A1: Date received | B1: Product | C1: Sub-product | D1: Issue | E1: Sub-issue | F1: Consumer complaint narrative | G1: Company public response | H1: Company | I1: State | J1: ZIP code | K1: Tags | L1: Submitted via | M1: Date sent to company | N1: Company response to consumer | O1: Timely response? | P1: Complaint ID | Q1: Days between sent date and received date
A2: 41046 | B2: Mortgage | C2: Other mortgage | D2: Loan modification,collection,foreclosure | H2: BANK OF AMERICA, NATIONAL ASSOCIATION | I2: CA | J2: 90242 | L2: Referral | M2: 41051 | N2: Closed with non-monetary relief | O2: No | P2: 81081 | Q2: =M2-A2 -> 5
A3: 41142 | B3: Mortgage | C3: Other mortgage | D3: Other | H3: BANK OF AMERICA, NATIONAL ASSOCIATION | I3: NY | J3: 11218 | L3: Postal mail | M3: 41142 | N3: Closed with explanation | O3: Yes | P3: 139273 | Q3: =M3-A3 -> 0
A4: 41264 | B4: Credit card | D4: Advertising and marketing | H4: SYNCHRONY BANK | I4: CA | J4: 91108 | L4: Fax | M4: 41264 | N4: Closed with explanation | O4: Yes | P4: 215434 | Q4: =M4-A4 -> 0
A5: 41274 | B5: Mortgage | C5: Other mortgage | D5: Loan modification,collection,foreclosure | H5: OCWEN LOAN SERVICING LLC | I5: MI | J5: 48320 | L5: Fax | M5: 41276 | N5: Closed with explanation | O5: Yes | P5: 215643 | Q5: =M5-A5 -> 2
A6: 41283 | B6: Mortgage | C6: Other mortgage | D6: Loan modification,collection,foreclosure | H6: WELLS FARGO BANK, NATIONAL ASSOCIATION | I6: CA | J6: 94590 | L6: Referral | M6: 41288 | N6: Closed with explanation | O6: Yes | P6: 224922 | Q6: =M6-A6 -> 5
A7: 41473 | B7: Debt collection | C7: Medical | D7: Cont'd attempts collect debt not owed | E7: Debt is not mine | H7: APEX Asset Management, LLC | I7: NJ | J7: 8031 | L7: Web | M7: 41509 | N7: Closed | O7: No | P7: 460443 | Q7: =M7-A7 -> 36
A8: 41826 | B8: Mortgage | C8: Conventional adjustable mortgage (ARM) | D8: Loan servicing, payments, escrow account | H8: Ditech Financial LLC | I8: FL | J8: 34714 | L8: Web | M8: 41826 | N8: Closed with explanation | O8: Yes | P8: 924254 | Q8: =M8-A8 -> 0
A9: 41884 | B9: Credit reporting | D9: Incorrect information on credit report | E9: Public record | H9: TRANSUNION INTERMEDIATE HOLDINGS, INC. | I9: FL | J9: 33928 | L9: Web | M9: 41884 | N9: Closed with explanation | O9: Yes | P9: 1009652 | Q9: =M9-A9 -> 0
A10: 41932 | B10: Credit card | D10: Identity theft / Fraud / Embezzlement | H10: SYNCHRONY BANK | I10: CA | J10: 91602 | L10: Postal mail | M10: 41936 | N10: Closed with explanation | O10: Yes | P10: 1077763 | Q10: =M10-A10 -> 4
A11: 41935 | B11: Mortgage | C11: Other mortgage | D11: Loan modification,collection,foreclosure | H11: BANK OF AMERICA, NATIONAL ASSOCIATION | I11: CA | J11: 92879 | L11: Referral | M11: 41940 | N11: Closed with explanation | O11: Yes | P11: 1084242 | Q11: =M11-A11 -> 5
A12: 42008 | B12: Consumer Loan | C12: Installment loan | D12: Managing the loan or lease | H12: SYNCHRONY BANK | I12: NJ | J12: 8901 | L12: Web | M12: 42012 | N12: Closed with monetary relief | O12: Yes | P12: 1179936 | Q12: =M12-A12 -> 4
A13: 42065 | B13: Debt collection | C13: Non-federal student loan | D13: Disclosure verification of debt | E13: Not disclosed as an attempt to collect | H13: Law Offices of Goldsmith & Hull A.P.C. | I13: CA | J13: 90008 | L13: Postal mail | M13: 42072 | N13: Closed with explanation | O13: No | P13: 1263989 | Q13: =M13-A13 -> 7
A14: 42355 | B14: Debt collection | C14: Medical | D14: Disclosure verification of debt | E14: Not given enough info to verify debt | H14: Alpine Credit, Inc | I14: CO | J14: 80017 | L14: Web | M14: 42355 | N14: Closed with explanation | O14: No | P14: 1706577 | Q14: =M14-A14 -> 0
A15: 42408 | B15: Credit reporting | D15: Incorrect information on credit report | E15: Account status | G15: Company chooses not to provide a public response | H15: EXPERIAN DELAWARE GP | I15: NC | J15: 27703 | L15: Postal mail | M15: 42408 | N15: Closed with explanation | O15: Yes | P15: 1776912 | Q15: =M15-A15 -> 0
A16: 42454 | B16: Debt collection | C16: Other (i.e. phone, health club, etc.) | D16: Disclosure verification of debt | E16: Not given enough info to verify debt | H16: Quality Recovery Services, Inc. | I16: GA | J16: 30014 | L16: Referral | M16: 42458 | N16: Closed with explanation | O16: No | P16: 1849932 | Q16: =M16-A16 -> 4
A17: 42489 | B17: Credit reporting | D17: Incorrect information on credit report | E17: Information is not mine | G17: Company has responded to the consumer and the CFPB and chooses not to provide a public response | H17: TRANSUNION INTERMEDIATE HOLDINGS, INC. | I17: NV | J17: 89031 | L17: Web | M17: 42489 | N17: Closed with explanation | O17: Yes | P17: 1901482 | Q17: =M17-A17 -> 0
A18: 42496 | B18: Debt collection | C18: Other (i.e. phone, health club, etc.) | D18: Cont'd attempts collect debt not owed | E18: Debt is not mine | F18: i gave a vehicle away signed a bill of sale and turned in a release of liability to the dmv 6 plus years after i have a report on my XXXX that i have a XXXX dollar debt for the vehicle after it was impounded.i contacted the reporting persons and was told that because the other party had not followed through i was responsible even though the XXXX couldnt find a record of me owning the vehicle.i tried working with this company providing all the info i could for them even though the dmv wasnt able to find my name attached to this vehicle and refused to investagate anything | H18: FINEX Group LLC | I18: CA | J18: 953XX | L18: Web | M18: 42496 | N18: Closed with explanation | O18: No | P18: 1914423 | Q18: =M18-A18 -> 0
A19: 42508 | B19: Mortgage | C19: Other mortgage | D19: Loan modification,collection,foreclosure | G19: Company has responded to the consumer and the CFPB and chooses not to provide a public response | H19: WELLS FARGO BANK, NATIONAL ASSOCIATION | I19: NJ | J19: 8618 | L19: Referral | M19: 42513 | N19: Closed with explanation | O19: Yes | P19: 1931957 | Q19: =M19-A19 -> 5
A20: 42549 | B20: Debt collection | C20: Other (i.e. phone, health club, etc.) | D20: Taking/threatening an illegal action | E20: Threatened to sue on too old debt | H20: Resurgent Capital Services L.P. | I20: MI | J20: 48219 | L20: Referral | M20: 42550 | N20: Closed with explanation | O20: Yes | P20: 1989521 | Q20: =M20-A20 -> 1
A21: 42682 | B21: Credit reporting | D21: Incorrect information on credit report | E21: Information is not mine | H21: EQUIFAX, INC. | I21: AZ | J21: 85296 | L21: Web | M21: 42682 | N21: Closed with explanation | O21: Yes | P21: 2199513 | Q21: =M21-A21 -> 0
A22: 42691 | B22: Debt collection | C22: Other (i.e. phone, health club, etc.) | D22: Disclosure verification of debt | E22: Not given enough info to verify debt | H22: PMGI, LLC | I22: CA | J22: 92356 | L22: Postal mail | M22: 42692 | N22: Closed with non-monetary relief | O22: No | P22: 2214174 | Q22: =M22-A22 -> 1
A23: 42692 | B23: Mortgage | C23: Conventional fixed mortgage | D23: Settlement process and costs | F23: Started the refinance of home mortgage process with cash out option on XX/XX/2016. Necessary documents were submitted by XXXX. After initial review, got good faith estimate with loan amount and closing cost. Based on this estimate, a deposit of {$350.00} was made towards appraisal. Appraisal came with lesser amount by {$5000.00}. Agreed to reduce the loan amount to that extent. However, got a revised estimate which was less by {$30000.00} and with additional closing cost towards points etc. In between got numerous revised estimates with different loan amounts and closing cost. It took more than 2 months to reach any definite closing document. Hence, want to get back the deposit of {$350.00}. | H23: AMERICAN NEIGHBORHOOD MORTGAGE | I23: NJ | J23: 088XX | L23: Web | M23: 42695 | N23: Closed with monetary relief | O23: No | P23: 2216206 | Q23: =M23-A23 -> 3
A24: 42699 | B24: Debt collection | C24: Other (i.e. phone, health club, etc.) | D24: Disclosure verification of debt | E24: Not given enough info to verify debt | H24: RR Resource-Recovery | I24: NY | J24: 13760 | L24: Web | M24: 42798 | N24: Closed with explanation | O24: Yes | P24: 2223190 | Q24: =M24-A24 -> 99
A25: 42772 | B25: Consumer Loan | C25: Installment loan | D25: Managing the loan or lease | F25: I have written to this company called Swiss Colony and disputed the item on my credit report and requested them to provide documentation bearing my signature associate with the account. They did not do so. I also let them know that the account may be fraudulent as well. I have an fraud alert on my credit files because of this company. I have looked at my credit report dated today ( XX/XX/2017 ) and before that date I did n't see the statement disputed by consumer in the remark area on my credit files. Instead in the remark area : Profit and loss write off. This statement is in the remark area. This company has broken the law called FCRA because they failed to place the statement : " disputed by consumer, '' and I do want the company to delete the entry from my credit files. I have requested this company to provide proof of any documentations bearing my signature with this account. They failed to do so with that being said I want the entry to be deleted immediately. | H25: Colony Brands, Inc. | I25: NC | J25: 278XX | L25: Web | M25: 42798 | N25: Untimely response | O25: No | P25: 2329445 | Q25: =M25-A25 -> 26
A26: 42794 | B26: Debt collection | C26: Other (i.e. phone, health club, etc.) | D26: Improper contact or sharing of info | E26: Contacted me after I asked not to | H26: EXPERT GLOBAL SOLUTIONS, INC. | L26: Web | M26: 42798 | N26: Closed with explanation | O26: Yes | P26: 2364897 | Q26: =M26-A26 -> 4
A27: 42795 | B27: Debt collection | C27: I do not know | D27: Improper contact or sharing of info | E27: Talked to a third party about my debt | H27: Bursey & Associates, P.C. | I27: AZ | J27: 85295 | L27: Web | M27: 42798 | N27: Closed with explanation | O27: Yes | P27: 2367513 | Q27: =M27-A27 -> 3
A28: 42795 | B28: Student loan | C28: Federal student loan servicing | D28: Dealing with my lender or servicer | E28: Trouble with how payments are handled | H28: AES/PHEAA | L28: Referral | M28: 42802 | N28: Closed with explanation | O28: Yes | P28: 2367674 | Q28: =M28-A28 -> 7
A29: 42796 | B29: Mortgage | C29: Conventional fixed mortgage | D29: Loan servicing, payments, escrow account | H29: Dovenmuehle Mortgage, Inc. | I29: CT | J29: 6360 | L29: Phone | M29: 42800 | N29: Closed with explanation | O29: Yes | P29: 2369802 | Q29: =M29-A29 -> 4
A30: 42798 | B30: Mortgage | C30: Conventional fixed mortgage | D30: Loan servicing, payments, escrow account | G30: Company believes it acted appropriately as authorized by contract or law | H30: Ditech Financial LLC | I30: MI | J30: 48328 | L30: Web | M30: 42798 | N30: Closed with explanation | O30: Yes | P30: 2371574 | Q30: =M30-A30 -> 0
A31: 42798 | B31: Debt collection | C31: Credit card | D31: Cont'd attempts collect debt not owed | E31: Debt is not mine | H31: Levy and Associates, LLC | I31: OH | J31: 43235 | L31: Web | M31: 42798 | N31: Closed with explanation | O31: Yes | P31: 2371593 | Q31: =M31-A31 -> 0
A32: 42798 | B32: Credit reporting | D32: Credit reporting company's investigation | E32: Inadequate help over the phone | H32: EQUIFAX, INC. | I32: NY | J32: 14610 | L32: Web | M32: 42798 | N32: Closed with explanation | O32: Yes | P32: 2371598 | Q32: =M32-A32 -> 0
A33: 42798 | B33: Debt collection | C33: Credit card | D33: Cont'd attempts collect debt not owed | E33: Debt resulted from identity theft | H33: Credit Card Receivables Fund Incorporated | I33: NC | J33: 27597 | L33: Web | M33: 42798 | N33: Closed with explanation | O33: Yes | P33: 2371600 | Q33: =M33-A33 -> 0
A34: 42798 | B34: Credit card | D34: Balance transfer | F34: Around XX/XX/XXXX I accepted a credit card offer from my Chase AARP card at a 0 % interest for a year with a 2 % transfer fee. Needing the money, I called Chase and asked them to deposit XXXX into my checking account and, shortly there after, they did so. Now, they are wanting the XXXX. back from my checking account. They say it was their error but they should n't have deposited the money because that checking account has n't been used to pay a Chase fee within 3 months, so could n't be approved for the transfer.. I had XXXX balances so there was no need to make a payment. They made this decision after they deposited the money into my account.They say they will pay the bank fees but where am I supposed to get the XXXX?. I do not have all of the XXXX left and what is there is allocated for checks and payments that have not cleared yet. I accepted their offer and borrowed this money in good faith and have spent many hours on the phone with various Chase reps and am that the account is active, has XXXX available credit, but they can not assign the money already borrowed to that account because it was n't used for 3 months. Surely they can lift the rule to cover their error, but they wo n't. The woman, who said she was a manager, gave me the fax number of Chase Executive Offices as my only recourse. So, I am contacting you. This is an AARP card, available only to XXXX. They are causing havoc in my life and do not care at all. Please help | H34: JPMORGAN CHASE & CO. | I34: TN | J34: 376XX | K34: Older American | L34: Web | M34: 42798 | N34: Closed with monetary relief | O34: Yes | P34: 2371616 | Q34: =M34-A34 -> 0
A35: 42798 | B35: Mortgage | C35: Other mortgage | D35: Loan modification,collection,foreclosure | H35: JPMORGAN CHASE & CO. | I35: NC | J35: 28731 | K35: Older American | L35: Web | M35: 42798 | N35: Closed with explanation | O35: Yes | P35: 2371632 | Q35: =M35-A35 -> 0
A36: 42798 | B36: Bank account or service | C36: Other bank product/service | D36: Using a debit or ATM card | H36: Comerica | I36: NC | J36: 28405 | L36: Web | M36: 42798 | N36: Closed with explanation | O36: Yes | P36: 2371634 | Q36: =M36-A36 -> 0
A37: 42798 | B37: Debt collection | C37: Credit card | D37: Cont'd attempts collect debt not owed | E37: Debt resulted from identity theft | H37: ONEMAIN FINANCIAL HOLDINGS, LLC. | I37: NC | J37: 27597 | L37: Web | M37: 42798 | N37: Closed with explanation | O37: Yes | P37: 2371642 | Q37: =M37-A37 -> 0
A38: 42798 | B38: Credit reporting | D38: Credit reporting company's investigation | E38: Investigation took too long | H38: EQUIFAX, INC. | I38: CA | J38: 92683 | L38: Web | M38: 42798 | N38: Closed with explanation | O38: Yes | P38: 2371648 | Q38: =M38-A38 -> 0
A39: 42798 | B39: Student loan | C39: Federal student loan servicing | D39: Can't repay my loan | E39: Can't get flexible payment options | F39: I filed for chapter XXXX bankruptcy XX/XX/2011. I did go to school after filing. Notice of filing was provided to the Federal Loan employees when they called every week. They have continued to report late history on my credit report. A call was placed to them two weeks ago to address the issue with reporting negative payments. The rep stated they would correct as payments should have not been reported. When the reports were checked, it was noted that the accounts were reported as current under negative account information on XXXX, and showing 11 missed payments for the past two years on XXXX and XXXX reports. They should not be reporting negatively to any credit bureaus due to the active bankruptcy. The information should also be reported under the correct sections of the credit file. I am asking that the company report the information accurately on all the credit files as it has really added to the negative standard of my credit score | H39: AES/PHEAA | I39: TN | J39: 381XX | L39: Web | M39: 42798 | N39: Closed with explanation | O39: Yes | P39: 2371677 | Q39: =M39-A39 -> 0
A40: 42798 | B40: Debt collection | C40: Credit card | D40: Disclosure verification of debt | E40: Not given enough info to verify debt | H40: ONEMAIN FINANCIAL HOLDINGS, LLC. | I40: NC | J40: 27597 | L40: Web | M40: 42798 | N40: Closed with explanation | O40: Yes | P40: 2371691 | Q40: =M40-A40 -> 0
A41: 42798 | B41: Bank account or service | C41: Checking account | D41: Account opening, closing, or management | F41: My wife and I visited the Chase Bank branch at XXXX, XXXX, KY on XX/XX/2017 around XXXX AM to open new checking accounts. We were prompted to open these checking accounts because Chase mailed and emailed us vouchers to receive {$300.00} for opening each account and personal friends had also referred us. XXXX was assigned to assist us in this matter. His first question to us was " where do you work? ". After informing him that we are both were XXXX employees he asked us what we were going to do with our XXXX accounts. We advised him we would be keeping those accounts open. He then asked what we would be using our new Chase accounts for and I advised we would be using those accounts for miscellaneous savings, etc. It was then that XXXX XXXX advised he would not be opening the new accounts for us unless we closed our XXXX accounts and he tossed the Chase Voucher and our ID 's back across the desk to us ( RUDE! ). Confused, I questioned him further about this and he advised that he did not believe we were going to use our new Chase accounts and would just close them in 6 months. Upon clarifying that we would indeed keep the Chase accounts open and meet all of the requirements of the offer he stated that we would not be closing our XXXX accounts. He reiterated that he would not open the accounts for us and advised that he would get his manager XXXX involved. When XXXX XXXX arrived in the office to speak with us she advised that Chase would not be honoring the vouchers and would not open accounts for us because XXXX XXXX told her we were not planning to keep the accounts open and would not be " using '' the accounts. I advised XXXX XXXX that we intended to meet the minimum requirements ( set up direct deposit and keep the account open for 6 months ) and would keep the accounts open further if we enjoyed the service we received from Chase during that time. I advised we intended to have direct deposit active on the accounts and would be moving money in and out of the accounts, but she did not seem to believe that was qualifying usage of the accounts. She then advised that I had previously opened a Chase account with a coupon about 10 years ago and did not keep it open. However, I believe that account was my primary checking account and I did keep it open for the required period of time and more. It was only when I moved out of state that I closed the account because I did not know if there would be Chase branches in my new area. I am deeply insulted by my experience in trying to open these new accounts and feel that my wife and I have been discriminated against because of our employment with another banking institute. In addition to this occurrence while my wife and I we waiting in the lobby to meet with XXXX XXXX we both were able to clearly observe XXXX 's business interactions with another customer who was in his cubicle/office which has an open door and clear glass windows. We were able to hear their entire conversation and at a certain point XXXX XXXX pulled that customer 's XXXX score. After pulling the XXXX score up on his monitor he swiveled the monitor around so that it was facing directly out the window into the lobby and I could clearly see the customer 's score was XXXX. Being in the banking business I understand well that this is a clear violation of Customer Confidentiality regulations and should be dealt with as such. | H41: JPMORGAN CHASE & CO. | I41: KY | J41: 423XX | L41: Web | M41: 42798 | N41: Closed with explanation | O41: Yes | P41: 2371744 | Q41: =M41-A41 -> 0
A42: 42798 | B42: Credit reporting | D42: Credit reporting company's investigation | E42: Problem with statement of dispute | H42: EQUIFAX, INC. | I42: GA | J42: 30122 | L42: Web | M42: 42798 | N42: Closed with explanation | O42: Yes | P42: 2371764 | Q42: =M42-A42 -> 0
A43: 42798 | B43: Debt collection | C43: Other (i.e. phone, health club, etc.) | D43: Disclosure verification of debt | E43: Not given enough info to verify debt | H43: Southwest Credit Systems, L.P. | I43: ME | J43: 4069 | L43: Web | M43: 42798 | N43: Closed with explanation | O43: Yes | P43: 2371781 | Q43: =M43-A43 -> 0
A44: 42798 | B44: Debt collection | C44: Credit card | D44: Communication tactics | E44: Threatened to take legal action | H44: ENCORE CAPITAL GROUP INC. | I44: MD | J44: 21244 | L44: Web | M44: 42798 | N44: Closed with non-monetary relief | O44: Yes | P44: 2371786 | Q44: =M44-A44 -> 0
A45: 42798 | B45: Credit reporting | D45: Incorrect information on credit report | E45: Personal information | H45: EQUIFAX, INC. | I45: NJ | J45: 7843 | L45: Web | M45: 42798 | N45: Closed with non-monetary relief | O45: Yes | P45: 2371789 | Q45: =M45-A45 -> 0
A46: 42798 | B46: Debt collection | C46: Other (i.e. phone, health club, etc.) | D46: Improper contact or sharing of info | E46: Talked to a third party about my debt | H46: Resurgent Capital Services L.P. | I46: TX | J46: 75686 | L46: Web | M46: 42798 | N46: Closed with explanation | O46: Yes | P46: 2371815 | Q46: =M46-A46 -> 0
A47: 42798 | B47: Bank account or service | C47: Other bank product/service | D47: Account opening, closing, or management | H47: CAPITAL ONE FINANCIAL CORPORATION | I47: MD | J47: 20852 | L47: Web | M47: 42798 | N47: Closed with explanation | O47: Yes | P47: 2371846 | Q47: =M47-A47 -> 0
A48: 42798 | B48: Debt collection | C48: Other (i.e. phone, health club, etc.) | D48: Taking/threatening an illegal action | E48: Sued w/o proper notification of suit | F48: I am being sued for Non-Payment, but all payments have been sent on time as agreed, the payment in XXXX was returned said no such address in XXXX error, I immediately mailed payment back, they acknowledge the received on XX/XX/2017, this was only XXXX business days late, then I received letter impending legal action as well for Non-Payment, the received payment pry to sending letter, I feel this legal action is unnecessary and unwarranted, I am continuing to make payments on time as agreed. I was not properly served, I found the Warrant some distance outside my residence, and mailed from Debt Collector at letter date. When I tried to talk to the Debt Collector after receive letter of impending legal action, she would not or could not stop legal action, and was unwilling to compromise or resolve this issue due to XXXX error, and just wanted to add additional fees, the Debt Collector was unprofessional, insulting, and among other statements said I lack common sense. If they are granted a judgment I will have insufficient funds for housing expenses. | H48: Results Unlimited, Inc. | I48: VA | J48: 224XX | L48: Web | M48: 42798 | N48: Closed with non-monetary relief | O48: No | P48: 2371864 | Q48: =M48-A48 -> 0
A49: 42798 | B49: Credit reporting | D49: Incorrect information on credit report | E49: Information is not mine | H49: EQUIFAX, INC. | I49: PA | J49: 19148 | K49: Servicemember | L49: Web | M49: 42798 | N49: Closed with explanation | O49: Yes | P49: 2371893 | Q49: =M49-A49 -> 0
A50: 42798 | B50: Student loan | C50: Federal student loan servicing | D50: Can't repay my loan | E50: Can't decrease my monthly payments | F50: The service representative was harsh and not listening to my questions. Attempting to collect on a debt I thought was in a grace period because I had just finished school in XXXX and it is only XXXX. Why would know one contact me prior to this? I let her know I could n't afford the XXXX a month and I needed to lower my payments. They were aggressive and unwilling to hear it. I fully intend on paying my loans just needs to be something I can afford monthly as to not overextend myself. Hate that my loans even ended up with Navient. | H50: Navient Solutions, LLC. | I50: OK | J50: 741XX | L50: Web | M50: 42798 | N50: Closed with explanation | O50: Yes | P50: 2371928 | Q50: =M50-A50 -> 0
A51: 42798 | B51: Consumer Loan | C51: Vehicle loan | D51: Problems when you are unable to pay | H51: PRESTIGE FINANCIAL SERVICES INC | I51: IL | J51: 60653 | L51: Web | M51: 42798 | N51: Closed with explanation | O51: Yes | P51: 2371938 | Q51: =M51-A51 -> 0
A52: 42799 | B52: Debt collection | C52: I do not know | D52: Cont'd attempts collect debt not owed | E52: Debt resulted from identity theft | F52: I 've sent multiple letters to this agency about this not being my account. After being advised by identitytheft.gov I 've completed and sent a fraud affidavit via certified mail. I can see they received it but nothing has changed. See supporting documents. even the USPS tracking. I am a victim of identity theft and noticed a collection from NCC BUSINESS SERVICES I 've attempted to dispute multiple times however no response on their end. Not sure what else to do. Police department told me to contact the federal trade commision which I wrote a formal complaint against NCC BUSINESS SERVICES in regards to this matter. The FTC also instructed me to complete a id theft affidavit through identity theft.gov. Attached is my document. Thank you | G52: Company has responded to the consumer and the CFPB and chooses not to provide a public response | H52: NCC Business Services, Inc. | I52: TX | J52: 775XX | L52: Web | M52: 42799 | N52: Closed with explanation | O52: Yes | P52: 2372209 | Q52: =M52-A52 -> 0
A53: 42800 | B53: Credit reporting | D53: Incorrect information on credit report | E53: Account status | F53: XXXX has wrongfully placed an account in collections. XXXX has indicated that I owed {$1700.00} for water bills at XXXX. This is absolutely false. All of the bills were in good standing upon leaving. This company bulldogged and bullied me into leaving the property. They initiated an eviction on me when all of the rents were paid on time. Elite home management has placed this account in collection with National Credit Systems. I would like this account removed from collections immediately. Attached is full documentation that this account was paid in full. Additionally, XXXX kept my deposit. I would like to request my deposit be returned as I left the property in good standing and was NEVER late paying monthly rent. Please see all attached documentation. Furthermore, the claim that XXXX is stating I owe monies for a water bill is false. The amount started in XXXX of 2012. The account was never placed in my name and started with a balance of over {$700.00}! XXXX presented false documents to the court in order to have me evicted from the property. I 'm requesting that this is immediately removed from my credit report and handled outside of a credit reporting agency as these claims are false! | G53: Company believes it acted appropriately as authorized by contract or law | H53: National Credit Systems,Inc. | I53: GA | J53: 300XX | L53: Web | M53: 42802 | N53: Closed with explanation | O53: Yes | P53: 2373228 | Q53: =M53-A53 -> 2
A54: 42801 | B54: Debt collection | C54: Other (i.e. phone, health club, etc.) | D54: Communication tactics | E54: Frequent or repeated calls | H54: ONEMAIN FINANCIAL HOLDINGS, LLC. | I54: NJ | J54: 7111 | L54: Phone | M54: 42801 | N54: Closed with explanation | O54: Yes | P54: 2374511 | Q54: =M54-A54 -> 0
A55: 42804 | B55: Debt collection | C55: Mortgage | D55: Disclosure verification of debt | E55: Not given enough info to verify debt | H55: CARRINGTON MORTGAGE SERVICES | I55: NJ | J55: 7747 | L55: Referral | M55: 42808 | N55: Closed with explanation | O55: Yes | P55: 2380778 | Q55: =M55-A55 -> 4
A56: 42804 | B56: Mortgage | C56: Home equity loan or line of credit | D56: Loan modification,collection,foreclosure | G56: Company has responded to the consumer and the CFPB and chooses not to provide a public response | H56: BANK OF AMERICA, NATIONAL ASSOCIATION | I56: WA | J56: 98532 | K56: Older American, Servicemember | L56: Fax | M56: 42808 | N56: Closed with explanation | O56: Yes | P56: 2381695 | Q56: =M56-A56 -> 4
A57: 42807 | B57: Debt collection | C57: I do not know | D57: Cont'd attempts collect debt not owed | E57: Debt was paid | F57: I have not been contacted about this negative balance. I believe its through Alpine Credit or XXXX. This account was positive before I closed it and I do not understand why its still negative. I would like to get this issue resolved immediately because it is affecting my credit score immensely. I have had no debt collector call me or any mail correspondence delivered to me. | G57: Company disputes the facts presented in the complaint | H57: Alpine Credit, Inc | I57: AR | J57: 729XX | L57: Web | M57: 42809 | N57: Closed with explanation | O57: No | P57: 2383241 | Q57: =M57-A57 -> 2
A58: 42811 | B58: Debt collection | C58: Credit card | D58: Disclosure verification of debt | E58: Not given enough info to verify debt | G58: Company has responded to the consumer and the CFPB and chooses not to provide a public response | H58: CITIBANK, N.A. | I58: LA | J58: 71292 | L58: Web | M58: 42812 | N58: Closed with non-monetary relief | O58: Yes | P58: 2389782 | Q58: =M58-A58 -> 1
A59: 42810 | B59: Mortgage | C59: Other mortgage | D59: Application, originator, mortgage broker | G59: Company believes the complaint is the result of a misunderstanding | H59: MORTGAGE 4 U LLC | I59: VA | J59: 20176 | L59: Web | M59: 42844 | N59: Closed with explanation | O59: Yes | P59: 2390487 | Q59: =M59-A59 -> 34
A60: 42811 | B60: Bank account or service | C60: Checking account | D60: Making/receiving payments, sending money | G60: Company believes it acted appropriately as authorized by contract or law | H60: UNITED SERVICES AUTOMOBILE ASSOCIATION | I60: WI | J60: 54005 | L60: Referral | M60: 42814 | N60: Closed with explanation | O60: Yes | P60: 2393048 | Q60: =M60-A60 -> 3
A61: 42815 | B61: Credit card | D61: Identity theft / Fraud / Embezzlement | H61: CAPITAL ONE FINANCIAL CORPORATION | I61: FL | J61: 32255 | L61: Web | M61: 42816 | N61: Closed with monetary relief | O61: Yes | P61: 2395796 | Q61: =M61-A61 -> 1
A62: 42815 | B62: Credit reporting | D62: Incorrect information on credit report | E62: Information is not mine | F62: disputed incorrect information and accounts with experian, after thitry day was told accounts and bankruptcies showing on my report we verified as being mine when asked for proof was told they do not have to give me prooof informed rep i have been a victim of identity theft was told to send in affidavit and police report which i did send in was told under reinvestigation after thirt days went by again was told again accounts have been verfied as being mine again asked for proof some thing with mysignature on it or copy of drivers license said again they dont have to supply me with proof. | G62: Company has responded to the consumer and the CFPB and chooses not to provide a public response | H62: EXPERIAN DELAWARE GP | I62: IL | J62: 605XX | L62: Web | M62: 42815 | N62: Closed with non-monetary relief | O62: Yes | P62: 2397046 | Q62: =M62-A62 -> 0
A63: 42815 | B63: Credit reporting | D63: Incorrect information on credit report | E63: Information is not mine | G63: Company has responded to the consumer and the CFPB and chooses not to provide a public response | H63: EXPERIAN DELAWARE GP | I63: TX | J63: 77075 | K63: Older American | L63: Phone | M63: 42815 | N63: Closed with non-monetary relief | O63: Yes | P63: 2397100 | Q63: =M63-A63 -> 0
A64: 42815 | B64: Credit reporting | D64: Incorrect information on credit report | E64: Account terms | G64: Company has responded to the consumer and the CFPB and chooses not to provide a public response | H64: EXPERIAN DELAWARE GP | I64: FL | J64: 34275 | L64: Web | M64: 42815 | N64: Closed with explanation | O64: Yes | P64: 2397793 | Q64: =M64-A64 -> 0
A65: 42815 | B65: Credit reporting | D65: Incorrect information on credit report | E65: Account terms | G65: Company has responded to the consumer and the CFPB and chooses not to provide a public response | H65: EXPERIAN DELAWARE GP | I65: NY | J65: 11226 | L65: Web | M65: 42815 | N65: Closed with non-monetary relief | O65: Yes | P65: 2397805 | Q65: =M65-A65 -> 0
A66: 42816 | B66: Credit reporting | D66: Incorrect information on credit report | E66: Account terms | G66: Company has responded to the consumer and the CFPB and chooses not to provide a public response | H66: EXPERIAN DELAWARE GP | I66: CA | J66: 93313 | L66: Web | M66: 42816 | N66: Closed with explanation | O66: Yes | P66: 2397947 | Q66: =M66-A66 -> 0
A67: 42815 | B67: Credit reporting | D67: Incorrect information on credit report | E67: Information is not mine | G67: Company has responded to the consumer and the CFPB and chooses not to provide a public response | H67: EXPERIAN DELAWARE GP | I67: WI | J67: 53405 | L67: Web | M67: 42815 | N67: Closed with explanation | O67: Yes | P67: 2398113 | Q67: =M67-A67 -> 0
A68: 42815 | B68: Credit reporting | D68: Incorrect information on credit report | E68: Account status | F68: Experian reporting of XXXX XXXX reflects a foreflosure. this was a short sale of the property done on XX/XX/2013. this is not reported accurately | G68: Company has responded to the consumer and the CFPB and chooses not to provide a public response | H68: EXPERIAN DELAWARE GP | I68: PA | J68: 190XX | L68: Web | M68: 42815 | N68: Closed with explanation | O68: Yes | P68: 2398200 | Q68: =M68-A68 -> 0
A69: 42815 | B69: Credit reporting | D69: Incorrect information on credit report | E69: Information is not mine | G69: Company has responded to the consumer and the CFPB and chooses not to provide a public response | H69: EXPERIAN DELAWARE GP | I69: NC | J69: 28216 | L69: Web | M69: 42815 | N69: Closed with non-monetary relief | O69: Yes | P69: 2398377 | Q69: =M69-A69 -> 0
A70: 42817 | B70: Credit reporting | D70: Incorrect information on credit report | E70: Information is not mine | H70: On-Site Manager, Inc. | I70: AZ | J70: 850XX | L70: Web | M70: 42817 | N70: Closed with explanation | O70: No | P70: 2399826 | Q70: =M70-A70 -> 0
A71: 42816 | B71: Credit reporting | D71: Credit monitoring or identity protection | E71: Problem with fraud alerts | G71: Company has responded to the consumer and the CFPB and chooses not to provide a public response | H71: EXPERIAN DELAWARE GP | I71: GA | J71: 30309 | L71: Referral | M71: 42816 | N71: Closed with explanation | O71: Yes | P71: 2399982 | Q71: =M71-A71 -> 0
A72: 42817 | B72: Consumer Loan | C72: Pawn loan | D72: Applied for loan/did not receive money | F72: Several years ago I got a line of credit loan with Wachovia.They have since bin bought out by Wells Fargo.Years ago I applied to increase the amount.I was denied because my home does not rest on a permanent foundation.I did n't argue due to the change of regulations with the stock market crash.I have recently acquired about changing the amount again.I was told they could not prevent me from filling out the application but the result would be the same.I find it aggravating that I spent my life paying bills and maintaining a good credit score ; only to be judged by my house not being on a permanent foundation.I told them I felt I was being discriminated against.They replied it was about equity.My house has bin paid off for several years and is worth more than I am asking for.I believe this is a one size fits all policy and is not fair to the individual. | G72: Company has responded to the consumer and the CFPB and chooses not to provide a public response | H72: WELLS FARGO BANK, NATIONAL ASSOCIATION | I72: PA | J72: 182XX | K72: Servicemember | L72: Web | M72: 42817 | N72: Closed with explanation | O72: Yes | P72: 2401871 | Q72: =M72-A72 -> 0
A73: 42821 | B73: Mortgage | C73: Conventional fixed mortgage | D73: Loan servicing, payments, escrow account | H73: Nationwide Biweekly Administration, Inc. | I73: TX | J73: 78705 | K73: Older American | L73: Web | M73: 42821 | N73: Closed with explanation | O73: Yes | P73: 2404727 | Q73: =M73-A73 -> 0
A74: 42822 | B74: Credit card | D74: Payoff process | H74: CAPITAL ONE FINANCIAL CORPORATION | I74: MN | J74: 554XX | L74: Web | M74: 42822 | N74: Closed with explanation | O74: Yes | P74: 2406906 | Q74: =M74-A74 -> 0
A75: 42824 | B75: Mortgage | C75: Conventional fixed mortgage | D75: Loan servicing, payments, escrow account | H75: BAYVIEW LOAN SERVICING, LLC | I75: AZ | J75: 852XX | K75: Older American | L75: Web | M75: 42824 | N75: Closed with explanation | O75: Yes | P75: 2410895 | Q75: =M75-A75 -> 0
A76: 42824 | B76: Credit reporting | D76: Incorrect information on credit report | E76: Information is not mine | H76: WELLS FARGO BANK, NATIONAL ASSOCIATION | I76: SC | J76: 292XX | K76: Servicemember | L76: Web | M76: 42851 | N76: In progress | O76: Yes | P76: 2410915 | Q76: =M76-A76 -> 27
A77: 42825 | B77: Mortgage | C77: Conventional adjustable mortgage (ARM) | D77: Loan modification,collection,foreclosure | G77: Company has responded to the consumer and the CFPB and chooses not to provide a public response | H77: MUFG UNION BANK, NATIONAL ASSOCIATION | I77: CA | J77: 92026 | L77: Web | M77: 42825 | N77: Closed with explanation | O77: Yes | P77: 2411860 | Q77: =M77-A77 -> 0
A78: 42825 | B78: Mortgage | C78: Home equity loan or line of credit | D78: Loan servicing, payments, escrow account | F78: In XX/XX/2005 I obtained a home equity mortgage loan for {$46000.00} limit. I have been making all payments as required by EFT until the lender stopped taking the payments. I now believe the term of 10 years was apparently up. The lender now reports my loan delinquent which completely prevents me from refinancing. There were no warning signs along the way to let me know I would have to refinance or make other arrangements. The lender is now initiating foreclosure which I see as a way for them to steal my home legally. A should offer to reschedule or refinance the balance of {$23000.00} so I can resume payments. | G78: Company has responded to the consumer and the CFPB and chooses not to provide a public response | H78: BANK OF AMERICA, NATIONAL ASSOCIATION | I78: MP | J78: 554XX | L78: Web | M78: 42828 | N78: Closed with explanation | O78: Yes | P78: 2412732 | Q78: =M78-A78 -> 3
A79: 42825 | B79: Other financial service | C79: Money order | D79: Lost or stolen money order | F79: I bought a money order from XXXX XXXX to pay a bill. When I found out that the payment had not been credited, I traced the money order and found out it had been stolen and cashed, and that the thief had changed the name of the payor and the payee. I filed a police report and completed all the paperwork XXXX XXXX asked for in order to get the money order replaced. Then XXXX XXXX sent me a letter saying they had filed a claim on my behalf with the Bank of First Deposit ( Bank of America ) and that Bank of America had not responded, so XXXX XXXX was closing their investigation and that I should contact Bank of America. I contacted Bank of America, but they said it had nothing to do with them and that I had to go back to XXXX XXXX. When I did, XXXX XXXX told me I had to go to Bank of America. | G79: Company has responded to the consumer and the CFPB and chooses not to provide a public response | H79: BANK OF AMERICA, NATIONAL ASSOCIATION | I79: NY | J79: 100XX | L79: Web | M79: 42828 | N79: Closed with explanation | O79: Yes | P79: 2412744 | Q79: =M79-A79 -> 3
A80: 42825 | B80: Debt collection | C80: I do not know | D80: Disclosure verification of debt | E80: Right to dispute notice not received | G80: Company believes it acted appropriately as authorized by contract or law | H80: Source Receivables Management LLC | I80: IN | J80: 47807 | L80: Web | M80: 42858 | N80: Closed with explanation | O80: Yes | P80: 2414034 | Q80: =M80-A80 -> 33
A81: 42826 | B81: Credit reporting | D81: Improper use of my credit report | E81: Report improperly shared by CRC | H81: Fidelity National Information Services, Inc. (FNIS) | I81: MN | J81: 55406 | K81: Servicemember | L81: Web | M81: 42826 | N81: Closed with explanation | O81: Yes | P81: 2414640 | Q81: =M81-A81 -> 0
A82: 42826 | B82: Credit card | D82: Customer service / Customer relations | H82: CAPITAL ONE FINANCIAL CORPORATION | I82: TN | J82: 371XX | K82: Servicemember | L82: Web | M82: 42826 | N82: Closed with explanation | O82: Yes | P82: 2414717 | Q82: =M82-A82 -> 0
A83: 42829 | B83: Credit reporting | D83: Incorrect information on credit report | E83: Information is not mine | H83: EQUIFAX, INC. | I83: IN | J83: 46226 | L83: Phone | M83: 42829 | N83: Closed with non-monetary relief | O83: Yes | P83: 2416121 | Q83: =M83-A83 -> 0
A84: 42828 | B84: Credit reporting | D84: Incorrect information on credit report | E84: Information is not mine | H84: EQUIFAX, INC. | I84: IA | J84: 511XX | L84: Web | M84: 42828 | N84: Closed with explanation | O84: Yes | P84: 2416355 | Q84: =M84-A84 -> 0
A85: 42828 | B85: Bank account or service | C85: Checking account | D85: Deposits and withdrawals | G85: Company has responded to the consumer and the CFPB and chooses not to provide a public response | H85: BANK OF AMERICA, NATIONAL ASSOCIATION | I85: WA | J85: 98052 | L85: Referral | M85: 42829 | N85: Closed with explanation | O85: Yes | P85: 2416625 | Q85: =M85-A85 -> 1
A86: 42828 | B86: Credit reporting | D86: Incorrect information on credit report | E86: Public record | H86: EQUIFAX, INC. | I86: DC | J86: 20032 | L86: Web | M86: 42828 | N86: Closed with explanation | O86: Yes | P86: 2417137 | Q86: =M86-A86 -> 0
A87: 42829 | B87: Bank account or service | C87: (CD) Certificate of deposit | D87: Deposits and withdrawals | G87: Company has responded to the consumer and the CFPB and chooses not to provide a public response | H87: ALLY FINANCIAL INC. | I87: GA | J87: 30047 | L87: Web | M87: 42829 | N87: Closed with explanation | O87: Yes | P87: 2417442 | Q87: =M87-A87 -> 0
A88: 42829 | B88: Credit card | D88: Identity theft / Fraud / Embezzlement | H88: DISCOVER BANK | I88: NJ | J88: 8902 | L88: Referral | M88: 42830 | N88: Closed with explanation | O88: Yes | P88: 2418794 | Q88: =M88-A88 -> 1
A89: 42829 | B89: Bank account or service | C89: Other bank product/service | D89: Account opening, closing, or management | G89: Company has responded to the consumer and the CFPB and chooses not to provide a public response | H89: BANK OF AMERICA, NATIONAL ASSOCIATION | I89: WA | J89: 98023 | L89: Phone | M89: 42829 | N89: Closed with explanation | O89: Yes | P89: 2419089 | Q89: =M89-A89 -> 0
A90: 42829 | B90: Bank account or service | C90: Checking account | D90: Making/receiving payments, sending money | F90: I have been deprived of my income as Bank of America continues disappearing my direct deposit payments. In addition to their incapacity to secure people 's money 's, they are massively in mature as they trivialize their failures sending me an email saying : We got your back Fraud protection is back '' They are all very damaged organization full of arrogance and the belief that they are above the law. This is the fourth time I file a complaint against Bank of America and nothing happens to them. Had I done one inch of what they have done, I would have lost my license. How come they have more rights than the rest of the Americans? I I was supposed to receive moneys from XXXX {$290.00} on XX/XX/2017 and there is nothing in my account. Whe is the Federal government act as as a protector of the citizens who work for a living rather than the arrogant corporations destroying the citizens? | G90: Company has responded to the consumer and the CFPB and chooses not to provide a public response | H90: BANK OF AMERICA, NATIONAL ASSOCIATION | I90: MA | J90: 024XX | L90: Web | M90: 42829 | N90: Closed with explanation | O90: Yes | P90: 2419713 | Q90: =M90-A90 -> 0
A91: 42830 | B91: Bank account or service | C91: Savings account | D91: Account opening, closing, or management | F91: Ally Bank turned me down for deceased relative ( s ) debts. I owe no debts. Yet, the bank stated in their letter to me that since I have " outstanding debts '' I was turned down for a 1 % online savings account. There is no need to refer this complaint to another agency, I think XXXX is a flawed system for banks to use, and very few do n't use that to check potential banking clients credit, check history. | G91: Company has responded to the consumer and the CFPB and chooses not to provide a public response | H91: ALLY FINANCIAL INC. | I91: IL | J91: 600XX | L91: Web | M91: 42830 | N91: Closed with explanation | O91: Yes | P91: 2420825 | Q91: =M91-A91 -> 0
A92: 42831 | B92: Credit card | D92: Identity theft / Fraud / Embezzlement | H92: JPMORGAN CHASE & CO. | I92: DC | J92: 20002 | L92: Web | M92: 42831 | N92: Closed with explanation | O92: Yes | P92: 2421040 | Q92: =M92-A92 -> 0
A93: 42830 | B93: Mortgage | C93: Home equity loan or line of credit | D93: Application, originator, mortgage broker | G93: Company has responded to the consumer and the CFPB and chooses not to provide a public response | H93: BANK OF AMERICA, NATIONAL ASSOCIATION | I93: MD | J93: 20746 | L93: Referral | M93: 42831 | N93: Closed with non-monetary relief | O93: Yes | P93: 2421775 | Q93: =M93-A93 -> 1
A94: 42831 | B94: Debt collection | C94: Credit card | D94: Disclosure verification of debt | E94: Not given enough info to verify debt | G94: Company has responded to the consumer and the CFPB and chooses not to provide a public response | H94: CITIBANK, N.A. | I94: NY | J94: 11226 | L94: Web | M94: 42831 | N94: Closed with explanation | O94: Yes | P94: 2422048 | Q94: =M94-A94 -> 0
A95: 42831 | B95: Credit card | D95: Other fee | G95: Company has responded to the consumer and the CFPB and chooses not to provide a public response | H95: BARCLAYS BANK DELAWARE | I95: VA | J95: 22315 | K95: Servicemember | L95: Web | M95: 42831 | N95: Closed with explanation | O95: Yes | P95: 2423410 | Q95: =M95-A95 -> 0
A96: 42831 | B96: Prepaid card | C96: Mobile wallet | D96: Fraud or scam | H96: Blackhawk Network Holdings Inc. | I96: SC | J96: 292XX | L96: Web | M96: 42832 | N96: Closed with explanation | O96: Yes | P96: 2423435 | Q96: =M96-A96 -> 1
A97: 42832 | B97: Credit card | D97: Billing disputes | G97: Company has responded to the consumer and the CFPB and chooses not to provide a public response | H97: BARCLAYS BANK DELAWARE | I97: TX | J97: 79607 | K97: Servicemember | L97: Web | M97: 42832 | N97: Closed with explanation | O97: Yes | P97: 2423941 | Q97: =M97-A97 -> 0
A98: 42832 | B98: Mortgage | C98: Other mortgage | D98: Other | H98: OCWEN LOAN SERVICING LLC | I98: WA | J98: 98223 | L98: Postal mail | M98: 42832 | N98: Closed with explanation | O98: Yes | P98: 2424942 | Q98: =M98-A98 -> 0
A99: 42832 | B99: Mortgage | C99: FHA mortgage | D99: Loan modification,collection,foreclosure | H99: CARRINGTON MORTGAGE SERVICES | I99: FL | J99: 33441 | L99: Phone | M99: 42832 | N99: Closed with explanation | O99: Yes | P99: 2424946 | Q99: =M99-A99 -> 0
A100: 42832 | B100: Credit card | D100: APR or interest rate | G100: Company has responded to the consumer and the CFPB and chooses not to provide a public response | H100: BANK OF AMERICA, NATIONAL ASSOCIATION | I100: AZ | J100: 85296 | L100: Referral | M100: 42832 | N100: Closed with monetary relief | O100: Yes | P100: 2425048 | Q100: =M100-A100 -> 0
...

Sheet Geographical Insights
A1: State | B1: Number of complaints per state | C1: Perchentage of complaints per state | D1: Perchentage of complaints per state(rounded)
A2: AL | B2: =COUNTIF('Consumer Complaints'!I2:I201,'Geographical Insights'!A2) -> 1 | C2: =B2/SUM($B$2:$B$39) -> 0.0053763441 | D2: =_xlfn.CEILING.MATH(C2,0.01) -> 0.01
A3: AR | B3: =COUNTIF('Consumer Complaints'!I3:I202,'Geographical Insights'!A3) -> 1 | C3: =B3/SUM($B$2:$B$39) -> 0.0053763441 | D3: =_xlfn.CEILING.MATH(C3,0.01) -> 0.01
A4: AZ | B4: =COUNTIF('Consumer Complaints'!I4:I203,'Geographical Insights'!A4) -> 7 | C4: =B4/SUM($B$2:$B$39) -> 0.037634409 | D4: =_xlfn.CEILING.MATH(C4,0.01) -> 0.04
A5: CA | B5: =COUNTIF('Consumer Complaints'!I5:I204,'Geographical Insights'!A5) -> 25 | C5: =B5/SUM($B$2:$B$39) -> 0.1344086 | D5: =_xlfn.CEILING.MATH(C5,0.01) -> 0.14
A6: CO | B6: =COUNTIF('Consumer Complaints'!I6:I205,'Geographical Insights'!A6) -> 3 | C6: =B6/SUM($B$2:$B$39) -> 0.016129032 | D6: =_xlfn.CEILING.MATH(C6,0.01) -> 0.02
A7: CT | B7: =COUNTIF('Consumer Complaints'!I7:I206,'Geographical Insights'!A7) -> 2 | C7: =B7/SUM($B$2:$B$39) -> 0.010752688 | D7: =_xlfn.CEILING.MATH(C7,0.01) -> 0.02
A8: DC | B8: =COUNTIF('Consumer Complaints'!I8:I207,'Geographical Insights'!A8) -> 4 | C8: =B8/SUM($B$2:$B$39) -> 0.021505376 | D8: =_xlfn.CEILING.MATH(C8,0.01) -> 0.03
A9: FL | B9: =COUNTIF('Consumer Complaints'!I9:I208,'Geographical Insights'!A9) -> 10 | C9: =B9/SUM($B$2:$B$39) -> 0.053763441 | D9: =_xlfn.CEILING.MATH(C9,0.01) -> 0.06
A10: GA | B10: =COUNTIF('Consumer Complaints'!I10:I209,'Geographical Insights'!A10) -> 11 | C10: =B10/SUM($B$2:$B$39) -> 0.059139785 | D10: =_xlfn.CEILING.MATH(C10,0.01) -> 0.06
A11: IA | B11: =COUNTIF('Consumer Complaints'!I11:I210,'Geographical Insights'!A11) -> 1 | C11: =B11/SUM($B$2:$B$39) -> 0.0053763441 | D11: =_xlfn.CEILING.MATH(C11,0.01) -> 0.01
A12: IL | B12: =COUNTIF('Consumer Complaints'!I12:I211,'Geographical Insights'!A12) -> 7 | C12: =B12/SUM($B$2:$B$39) -> 0.037634409 | D12: =_xlfn.CEILING.MATH(C12,0.01) -> 0.04
A13: IN | B13: =COUNTIF('Consumer Complaints'!I13:I212,'Geographical Insights'!A13) -> 3 | C13: =B13/SUM($B$2:$B$39) -> 0.016129032 | D13: =_xlfn.CEILING.MATH(C13,0.01) -> 0.02
... A39: WI | B39: =COUNTIF('Consumer Complaints'!I39:I238,'Geographical Insights'!A39) -> 3 | C39: =B39/SUM($B$2:$B$39) -> 0.016129032 | D39: =_xlfn.CEILING.MATH(C39,0.01) -> 0.02

Sheet Statistical Insights
A1: Distinct Issue | E1: unici
A2: Incorrect information on credit report | E2: {=_xlfn.UNIQUE(A2:A201)} -> Incorrect information on credit report | F2: =COUNTIF($A$2:$A$201,E2) -> 22
A3: Disclosure verification of debt | E3: Disclosure verification of debt | F3: =COUNTIF($A$2:$A$201,E3) -> 19
A4: Other | E4: Other | F4: =COUNTIF($A$2:$A$201,E4) -> 5
A5: Loan modification,collection,foreclosure | E5: Loan modification,collection,foreclosure | F5: =COUNTIF($A$2:$A$201,E5) -> 14
A6: Credit determination | E6: Credit determination | F6: =COUNTIF($A$2:$A$201,E6) -> 3
A7: Disclosure verification of debt | E7: Loan servicing, payments, escrow account | F7: =COUNTIF($A$2:$A$201,E7) -> 22
A8: Loan servicing, payments, escrow account | B8: ="Moda = "&E2&";"&E7 -> Moda = Incorrect information on credit report;Loan servicing, payments, escrow account | E8: Making/receiving payments, sending money | F8: =COUNTIF($A$2:$A$201,E8) -> 4
A9: Loan modification,collection,foreclosure | E9: Settlement process and costs | F9: =COUNTIF($A$2:$A$201,E9) -> 1
A10: Making/receiving payments, sending money | E10: Dealing with my lender or servicer | F10: =COUNTIF($A$2:$A$201,E10) -> 5
A11: Settlement process and costs | E11: Fraud or scam | F11: =COUNTIF($A$2:$A$201,E11) -> 2
A12: Dealing with my lender or servicer | E12: Account opening, closing, or management | F12: =COUNTIF($A$2:$A$201,E12) -> 16
A13: Fraud or scam | E13: Can't repay my loan | F13: =COUNTIF($A$2:$A$201,E13) -> 5
A14: Disclosure verification of debt | E14: Problems when you are unable to pay | F14: =COUNTIF($A$2:$A$201,E14) -> 4
A15: Loan modification,collection,foreclosure | E15: Credit reporting company's investigation | F15: =COUNTIF($A$2:$A$201,E15) -> 3
A16: Account opening, closing, or management | E16: Other fee | F16: =COUNTIF($A$2:$A$201,E16) -> 2
A17: Loan servicing, payments, escrow account | E17: Advertising, marketing or disclosures | F17: =COUNTIF($A$2:$A$201,E17) -> 1
A18: Loan modification,collection,foreclosure | E18: Improper contact or sharing of info | F18: =COUNTIF($A$2:$A$201,E18) -> 3
A19: Account opening, closing, or management | E19: Identity theft / Fraud / Embezzlement | F19: =COUNTIF($A$2:$A$201,E19) -> 5
A20: Can't repay my loan | E20: Customer service / Customer relations | F20: =COUNTIF($A$2:$A$201,E20) -> 1
... A46: Loan servicing, payments, escrow account | E46: Lost or stolen money order | F46: =COUNTIF($A$2:$A$201,E46) -> 1
A47: Loan modification,collection,foreclosure
A48: Problems caused by my funds being low
A49: Deposits and withdrawals
A50: Other
A51: Incorrect information on credit report
A52: Managing the loan or lease
A53: APR or interest rate
A54: Disclosure verification of debt
A55: Incorrect information on credit report
A56: Incorrect information on credit report
A57: Making/receiving payments, sending money
A58: Loan modification,collection,foreclosure
... A201: Incorrect information on credit report
